avaxtar/Avax_NN.py
avaxtar/Avaxtar.py
avaxtar/DF_from_DICT.py
avaxtar/Example.py
avaxtar/__init__.py
avaxtar/model_pytorch1.pt
avaxtar/scaler1.joblib
avaxtar-0.0.8.dist-info/LICENSE
avaxtar-0.0.8.dist-info/METADATA
avaxtar-0.0.8.dist-info/WHEEL
avaxtar-0.0.8.dist-info/dependency_links.txt
avaxtar-0.0.8.dist-info/top_level.txt
avaxtar-0.0.8.dist-info/RECORD
